<?xml version="1.0" encoding="utf-8"?><PARAMS><PARAM ID="1524442516" OBJECTID="165099636" CHANGEID="600578151" CHANGEIDEND="0" TYPEID="7" VALUE="98626101001" UPDATEDATE="2024-09-06" STARTDATE="2024-09-06" ENDDATE="2079-06-06" /><PARAM ID="1524442517" OBJECTID="165099636" CHANGEID="600578151" CHANGEIDEND="0" TYPEID="6" VALUE="98409000000" UPDATEDATE="2024-09-06" STARTDATE="2024-09-06" ENDDATE="2079-06-06" /><PARAM ID="1524442518" OBJECTID="165099636" CHANGEID="600578151" CHANGEIDEND="0" TYPEID="2" VALUE="1400" UPDATEDATE="2024-09-06" STARTDATE="2024-09-06" ENDDATE="2079-06-06" /><PARAM ID="1524442519" OBJECTID="165099636" CHANGEID="600578151" CHANGEIDEND="0" TYPEID="1" VALUE="1400" UPDATEDATE="2024-09-06" STARTDATE="2024-09-06" ENDDATE="2079-06-06" /><PARAM ID="1524442520" OBJECTID="165099636" CHANGEID="600578151" CHANGEIDEND="0" TYPEID="10" VALUE="14021001000015500" UPDATEDATE="2024-09-06" STARTDATE="2024-09-06" ENDDATE="2079-06-06" /><PARAM ID="1524442521" OBJECTID="165099636" CHANGEID="600578151" CHANGEIDEND="0" TYPEID="15" VALUE="263" UPDATEDATE="2024-09-06" STARTDATE="2024-09-06" ENDDATE="2079-06-06" /><PARAM ID="1524442522" OBJECTID="165099636" CHANGEID="600578151" CHANGEIDEND="0" TYPEID="13" VALUE="986261010010000026301" UPDATEDATE="2024-09-06" STARTDATE="2024-09-06" ENDDATE="2079-06-06" /><PARAM ID="1524442523" OBJECTID="165099636" CHANGEID="600578151" CHANGEIDEND="0" TYPEID="21" VALUE="98626101" UPDATEDATE="2024-09-06" STARTDATE="2024-09-06" ENDDATE="2079-06-06" /><PARAM ID="3385621" OBJECTID="220181" CHANGEID="566019" CHANGEIDEND="600890968" TYPEID="10" VALUE="14033000001006201" UPDATEDATE="2024-09-11" STARTDATE="1900-01-01" ENDDATE="2024-09-11" /><PARAM ID="1525274589" OBJECTID="220181" CHANGEID="600890968" CHANGEIDEND="0" TYPEID="10" VALUE="14033000001006200" UPDATEDATE="2024-09-11" STARTDATE="2024-09-11" ENDDATE="2079-06-06" /><PARAM ID="1525274590" OBJECTID="220181" CHANGEID="600890968" CHANGEIDEND="0" TYPEID="13" VALUE="986584700000000006211" UPDATEDATE="2024-09-11" STARTDATE="2024-09-11" ENDDATE="2079-06-06" /><PARAM ID="1525293167" OBJECTID="165199750" CHANGEID="600896671" CHANGEIDEND="0" TYPEID="4" VALUE="1421" UPDATEDATE="2024-09-11" STARTDATE="2024-09-11" ENDDATE="2079-06-06" /><PARAM ID="1525293168" OBJECTID="165199750" CHANGEID="600896671" CHANGEIDEND="0" TYPEID="3" VALUE="1421" UPDATEDATE="2024-09-11" STARTDATE="2024-09-11" ENDDATE="2079-06-06" /><PARAM ID="1525293169" OBJECTID="165199750" CHANGEID="600896671" CHANGEIDEND="0" TYPEID="2" VALUE="1400" UPDATEDATE="2024-09-11" STARTDATE="2024-09-11" ENDDATE="2079-06-06" /><PARAM ID="1525293170" OBJECTID="165199750" CHANGEID="600896671" CHANGEIDEND="0" TYPEID="1" VALUE="1400" UPDATEDATE="2024-09-11" STARTDATE="2024-09-11" ENDDATE="2079-06-06" /><PARAM ID="1525293171" OBJECTID="165199750" CHANGEID="600896671" CHANGEIDEND="0" TYPEID="7" VALUE="98641470" UPDATEDATE="2024-09-11" STARTDATE="2024-09-11" ENDDATE="2079-06-06" /><PARAM ID="1525293172" OBJECTID="165199750" CHANGEID="600896671" CHANGEIDEND="0" TYPEID="6" VALUE="98241870001" UPDATEDATE="2024-09-11" STARTDATE="2024-09-11" ENDDATE="2079-06-06" /><PARAM ID="1525293173" OBJECTID="165199750" CHANGEID="600896671" CHANGEIDEND="0" TYPEID="10" VALUE="14023000000000700" UPDATEDATE="2024-09-11" STARTDATE="2024-09-11" ENDDATE="2079-06-06" /><PARAM ID="1525293174" OBJECTID="165199750" CHANGEID="600896671" CHANGEIDEND="0" TYPEID="15" VALUE="1" UPDATEDATE="2024-09-11" STARTDATE="2024-09-11" ENDDATE="2079-06-06" /><PARAM ID="1525293175" OBJECTID="165199750" CHANGEID="600896671" CHANGEIDEND="0" TYPEID="13" VALUE="986414700000001000001" UPDATEDATE="2024-09-11" STARTDATE="2024-09-11" ENDDATE="2079-06-06" /><PARAM ID="1525293176" OBJECTID="165199750" CHANGEID="600896671" CHANGEIDEND="0" TYPEID="21" VALUE="98641470" UPDATEDATE="2024-09-11" STARTDATE="2024-09-11" ENDDATE="2079-06-06" /></PARAMS>