<?xml version="1.0" encoding="utf-8"?><PARAMS><PARAM ID="582306638" OBJECTID="81947178" CHANGEID="121766555" CHANGEIDEND="600763332" TYPEID="8" VALUE="68:10:1000034:81" UPDATEDATE="2024-09-09" STARTDATE="2018-10-04" ENDDATE="2024-09-09" /><PARAM ID="589684345" OBJECTID="79811575" CHANGEID="118619474" CHANGEIDEND="600751345" TYPEID="8" VALUE="68:07:08011003:257" UPDATEDATE="2024-09-09" STARTDATE="2018-07-31" ENDDATE="2024-09-09" /><PARAM ID="1524211676" OBJECTID="19550346" CHANGEID="600519993" CHANGEIDEND="0" TYPEID="8" VALUE="68:12:0601004:277" UPDATEDATE="2024-09-05" STARTDATE="2024-09-05" ENDDATE="2079-06-06" /><PARAM ID="1524211743" OBJECTID="44466474" CHANGEID="600520016" CHANGEIDEND="0" TYPEID="8" VALUE="68:12:0601004:327" UPDATEDATE="2024-09-05" STARTDATE="2024-09-05" ENDDATE="2079-06-06" /><PARAM ID="1524234574" OBJECTID="165068555" CHANGEID="600524823" CHANGEIDEND="0" TYPEID="8" VALUE="68:21:0202004:240" UPDATEDATE="2024-09-05" STARTDATE="2024-09-05" ENDDATE="2079-06-06" /><PARAM ID="1524234575" OBJECTID="165068555" CHANGEID="600524823" CHANGEIDEND="0" TYPEID="15" VALUE="1" UPDATEDATE="2024-09-05" STARTDATE="2024-09-05" ENDDATE="2079-06-06" /><PARAM ID="1524234576" OBJECTID="165068555" CHANGEID="600524823" CHANGEIDEND="0" TYPEID="13" VALUE="686424051060000000240007000100000" UPDATEDATE="2024-09-05" STARTDATE="2024-09-05" ENDDATE="2079-06-06" /><PARAM ID="1524242522" OBJECTID="165069614" CHANGEID="600526572" CHANGEIDEND="0" TYPEID="8" VALUE="68:21:0202004:254" UPDATEDATE="2024-09-05" STARTDATE="2024-09-05" ENDDATE="2079-06-06" /><PARAM ID="1524242523" OBJECTID="165069614" CHANGEID="600526572" CHANGEIDEND="0" TYPEID="15" VALUE="2" UPDATEDATE="2024-09-05" STARTDATE="2024-09-05" ENDDATE="2079-06-06" /><PARAM ID="1524242524" OBJECTID="165069614" CHANGEID="600526572" CHANGEIDEND="0" TYPEID="13" VALUE="686424051060000000240007000200000" UPDATEDATE="2024-09-05" STARTDATE="2024-09-05" ENDDATE="2079-06-06" /><PARAM ID="1524270680" OBJECTID="165074130" CHANGEID="600533157" CHANGEIDEND="0" TYPEID="8" VALUE="68:11:0601011:35" UPDATEDATE="2024-09-05" STARTDATE="2024-09-05" ENDDATE="2079-06-06" /><PARAM ID="1524270681" OBJECTID="165074130" CHANGEID="600533157" CHANGEIDEND="0" TYPEID="15" VALUE="1" UPDATEDATE="2024-09-05" STARTDATE="2024-09-05" ENDDATE="2079-06-06" /><PARAM ID="1524270682" OBJECTID="165074130" CHANGEID="600533157" CHANGEIDEND="0" TYPEID="13" VALUE="686204301010000000340002000100000" UPDATEDATE="2024-09-05" STARTDATE="2024-09-05" ENDDATE="2079-06-06" /><PARAM ID="1524270794" OBJECTID="165074145" CHANGEID="600533180" CHANGEIDEND="0" TYPEID="8" VALUE="68:11:0601011:34" UPDATEDATE="2024-09-05" STARTDATE="2024-09-05" ENDDATE="2079-06-06" /><PARAM ID="1524270795" OBJECTID="165074145" CHANGEID="600533180" CHANGEIDEND="0" TYPEID="15" VALUE="2" UPDATEDATE="2024-09-05" STARTDATE="2024-09-05" ENDDATE="2079-06-06" /><PARAM ID="1524270796" OBJECTID="165074145" CHANGEID="600533180" CHANGEIDEND="0" TYPEID="13" VALUE="686204301010000000340002000200000" UPDATEDATE="2024-09-05" STARTDATE="2024-09-05" ENDDATE="2079-06-06" /><PARAM ID="1524277920" OBJECTID="5150816" CHANGEID="600535409" CHANGEIDEND="0" TYPEID="8" VALUE="68:14:3501025:151" UPDATEDATE="2024-09-05" STARTDATE="2024-09-05" ENDDATE="2079-06-06" /><PARAM ID="1524281396" OBJECTID="78876066" CHANGEID="600536197" CHANGEIDEND="0" TYPEID="8" VALUE="68:16:0701002:66" UPDATEDATE="2024-09-05" STARTDATE="2024-09-05" ENDDATE="2079-06-06" /><PARAM ID="1524402439" OBJECTID="29155815" CHANGEID="600566256" CHANGEIDEND="0" TYPEID="8" VALUE="68:12:0601002:436" UPDATEDATE="2024-09-06" STARTDATE="2024-09-06" ENDDATE="2079-06-06" /><PARAM ID="1524402460" OBJECTID="29156166" CHANGEID="600566263" CHANGEIDEND="0" TYPEID="8" VALUE="68:12:0601002:447" UPDATEDATE="2024-09-06" STARTDATE="2024-09-06" ENDDATE="2079-06-06" /><PARAM ID="1524406477" OBJECTID="71429203" CHANGEID="600567464" CHANGEIDEND="0" TYPEID="8" VALUE="68:09:0301006:121" UPDATEDATE="2024-09-06" STARTDATE="2024-09-06" ENDDATE="2079-06-06" /><PARAM ID="1524428053" OBJECTID="29169149" CHANGEID="600574582" CHANGEIDEND="0" TYPEID="8" VALUE="68:12:0601002:193" UPDATEDATE="2024-09-06" STARTDATE="2024-09-06" ENDDATE="2079-06-06" /><PARAM ID="1524428892" OBJECTID="29169242" CHANGEID="600574791" CHANGEIDEND="0" TYPEID="8" VALUE="68:12:0601002:192" UPDATEDATE="2024-09-06" STARTDATE="2024-09-06" ENDDATE="2079-06-06" /><PARAM ID="1524429006" OBJECTID="29169636" CHANGEID="600574830" CHANGEIDEND="0" TYPEID="8" VALUE="68:12:0601002:190" UPDATEDATE="2024-09-06" STARTDATE="2024-09-06" ENDDATE="2079-06-06" /><PARAM ID="1524429337" OBJECTID="29169718" CHANGEID="600574902" CHANGEIDEND="0" TYPEID="8" VALUE="68:12:0601002:191" UPDATEDATE="2024-09-06" STARTDATE="2024-09-06" ENDDATE="2079-06-06" /><PARAM ID="1524429482" OBJECTID="29169726" CHANGEID="600574958" CHANGEIDEND="0" TYPEID="8" VALUE="68:12:0601002:194" UPDATEDATE="2024-09-06" STARTDATE="2024-09-06" ENDDATE="2079-06-06" /><PARAM ID="1524429639" OBJECTID="29169905" CHANGEID="600574994" CHANGEIDEND="0" TYPEID="8" VALUE="68:12:0601002:188" UPDATEDATE="2024-09-06" STARTDATE="2024-09-06" ENDDATE="2079-06-06" /><PARAM ID="1524466344" OBJECTID="65424815" CHANGEID="600584776" CHANGEIDEND="0" TYPEID="8" VALUE="68:12:0601002:279" UPDATEDATE="2024-09-06" STARTDATE="2024-09-06" ENDDATE="2079-06-06" /><PARAM ID="1524466553" OBJECTID="29170416" CHANGEID="600584817" CHANGEIDEND="0" TYPEID="8" VALUE="68:12:0601002:187" UPDATEDATE="2024-09-06" STARTDATE="2024-09-06" ENDDATE="2079-06-06" /><PARAM ID="1524473728" OBJECTID="29170685" CHANGEID="600586544" CHANGEIDEND="0" TYPEID="8" VALUE="68:12:2900004:5" UPDATEDATE="2024-09-06" STARTDATE="2024-09-06" ENDDATE="2079-06-06" /><PARAM ID="1524485003" OBJECTID="79194722" CHANGEID="600588543" CHANGEIDEND="0" TYPEID="8" VALUE="68:21:1101004:121" UPDATEDATE="2024-09-06" STARTDATE="2024-09-06" ENDDATE="2079-06-06" /><PARAM ID="1524513214" OBJECTID="83928496" CHANGEID="600594714" CHANGEIDEND="0" TYPEID="8" VALUE="68:21:1101003:59" UPDATEDATE="2024-09-06" STARTDATE="2024-09-06" ENDDATE="2079-06-06" /><PARAM ID="613377922" OBJECTID="12437941" CHANGEID="20077241" CHANGEIDEND="600596175" TYPEID="8" VALUE="68:68:08:009:2010:838" UPDATEDATE="2024-09-06" STARTDATE="2018-08-14" ENDDATE="2024-09-06" /><PARAM ID="1524616591" OBJECTID="40434936" CHANGEID="600681810" CHANGEIDEND="0" TYPEID="8" VALUE="68:07:0901002:427" UPDATEDATE="2024-09-06" STARTDATE="2024-09-06" ENDDATE="2079-06-06" /><PARAM ID="1524640613" OBJECTID="71759843" CHANGEID="600701630" CHANGEIDEND="0" TYPEID="8" VALUE="68:11:3401006:113" UPDATEDATE="2024-09-06" STARTDATE="2024-09-06" ENDDATE="2079-06-06" /><PARAM ID="1524640662" OBJECTID="53636070" CHANGEID="600701639" CHANGEIDEND="0" TYPEID="8" VALUE="68:14:0605004:378" UPDATEDATE="2024-09-06" STARTDATE="2024-09-06" ENDDATE="2079-06-06" /><PARAM ID="1524641011" OBJECTID="53617319" CHANGEID="600701690" CHANGEIDEND="0" TYPEID="8" VALUE="68:14:0605004:557" UPDATEDATE="2024-09-06" STARTDATE="2024-09-06" ENDDATE="2079-06-06" /><PARAM ID="1524641120" OBJECTID="53591449" CHANGEID="600701708" CHANGEIDEND="0" TYPEID="8" VALUE="68:14:0605004:256" UPDATEDATE="2024-09-06" STARTDATE="2024-09-06" ENDDATE="2079-06-06" /><PARAM ID="1524641267" OBJECTID="53659381" CHANGEID="600701759" CHANGEIDEND="0" TYPEID="8" VALUE="68:14:0605004:269" UPDATEDATE="2024-09-06" STARTDATE="2024-09-06" ENDDATE="2079-06-06" /><PARAM ID="1524641434" OBJECTID="53676859" CHANGEID="600701794" CHANGEIDEND="0" TYPEID="8" VALUE="68:14:0605004:289" UPDATEDATE="2024-09-06" STARTDATE="2024-09-06" ENDDATE="2079-06-06" /><PARAM ID="1524364777" OBJECTID="2354628" CHANGEID="600557678" CHANGEIDEND="600701785" TYPEID="8" VALUE="68:05:1004013:8" UPDATEDATE="2024-09-06" STARTDATE="2024-09-05" ENDDATE="2024-09-06" /><PARAM ID="1524641396" OBJECTID="2354628" CHANGEID="600701785" CHANGEIDEND="0" TYPEID="8" VALUE="68:05:1004009:23" UPDATEDATE="2024-09-06" STARTDATE="2024-09-06" ENDDATE="2079-06-06" /><PARAM ID="1524642956" OBJECTID="10847867" CHANGEID="600702018" CHANGEIDEND="0" TYPEID="8" VALUE="68:12:0606004:147" UPDATEDATE="2024-09-06" STARTDATE="2024-09-06" ENDDATE="2079-06-06" /><PARAM ID="1524643045" OBJECTID="28219667" CHANGEID="600702047" CHANGEIDEND="0" TYPEID="8" VALUE="68:12:0606002:172" UPDATEDATE="2024-09-06" STARTDATE="2024-09-06" ENDDATE="2079-06-06" /><PARAM ID="1524658150" OBJECTID="5125268" CHANGEID="600706187" CHANGEIDEND="0" TYPEID="8" VALUE="68:16:0701003:36" UPDATEDATE="2024-09-06" STARTDATE="2024-09-06" ENDDATE="2079-06-06" /><PARAM ID="1524658255" OBJECTID="52539305" CHANGEID="600706210" CHANGEIDEND="0" TYPEID="8" VALUE="68:16:0701006:117" UPDATEDATE="2024-09-06" STARTDATE="2024-09-06" ENDDATE="2079-06-06" /><PARAM ID="1524658254" OBJECTID="5920242" CHANGEID="600706209" CHANGEIDEND="0" TYPEID="8" VALUE="68:16:0407001:143" UPDATEDATE="2024-09-06" STARTDATE="2024-09-06" ENDDATE="2079-06-06" /><PARAM ID="1524658304" OBJECTID="5920082" CHANGEID="600706223" CHANGEIDEND="0" TYPEID="8" VALUE="68:16:0407001:142" UPDATEDATE="2024-09-06" STARTDATE="2024-09-06" ENDDATE="2079-06-06" /><PARAM ID="1524658299" OBJECTID="5120304" CHANGEID="600706220" CHANGEIDEND="0" TYPEID="8" VALUE="68:16:0701005:198" UPDATEDATE="2024-09-06" STARTDATE="2024-09-06" ENDDATE="2079-06-06" /><PARAM ID="1524727655" OBJECTID="165121716" CHANGEID="600745616" CHANGEIDEND="0" TYPEID="8" VALUE="68:29:0207001:3822" UPDATEDATE="2024-09-09" STARTDATE="2024-09-09" ENDDATE="2079-06-06" /><PARAM ID="1524727656" OBJECTID="165121716" CHANGEID="600745616" CHANGEIDEND="0" TYPEID="15" VALUE="1" UPDATEDATE="2024-09-09" STARTDATE="2024-09-09" ENDDATE="2079-06-06" /><PARAM ID="1524727657" OBJECTID="165121716" CHANGEID="600745616" CHANGEIDEND="0" TYPEID="13" VALUE="687010000010000042240012000100000" UPDATEDATE="2024-09-09" STARTDATE="2024-09-09" ENDDATE="2079-06-06" /><PARAM ID="1524727658" OBJECTID="165121717" CHANGEID="600745619" CHANGEIDEND="0" TYPEID="8" VALUE="68:29:0101046:523" UPDATEDATE="2024-09-09" STARTDATE="2024-09-09" ENDDATE="2079-06-06" /><PARAM ID="1524727659" OBJECTID="165121717" CHANGEID="600745619" CHANGEIDEND="0" TYPEID="15" VALUE="1" UPDATEDATE="2024-09-09" STARTDATE="2024-09-09" ENDDATE="2079-06-06" /><PARAM ID="1524727660" OBJECTID="165121717" CHANGEID="600745619" CHANGEIDEND="0" TYPEID="13" VALUE="687010000010000046940004000100000" UPDATEDATE="2024-09-09" STARTDATE="2024-09-09" ENDDATE="2079-06-06" /><PARAM ID="1524727720" OBJECTID="37011947" CHANGEID="600745646" CHANGEIDEND="0" TYPEID="8" VALUE="68:13:1601003:379" UPDATEDATE="2024-09-09" STARTDATE="2024-09-09" ENDDATE="2079-06-06" /><PARAM ID="1524727721" OBJECTID="37011714" CHANGEID="600745647" CHANGEIDEND="0" TYPEID="8" VALUE="68:13:1601003:380" UPDATEDATE="2024-09-09" STARTDATE="2024-09-09" ENDDATE="2079-06-06" /><PARAM ID="1524727724" OBJECTID="37017119" CHANGEID="600745649" CHANGEIDEND="0" TYPEID="8" VALUE="68:13:1601002:140" UPDATEDATE="2024-09-09" STARTDATE="2024-09-09" ENDDATE="2079-06-06" /><PARAM ID="1524727735" OBJECTID="37019972" CHANGEID="600745651" CHANGEIDEND="0" TYPEID="8" VALUE="68:13:1601003:382" UPDATEDATE="2024-09-09" STARTDATE="2024-09-09" ENDDATE="2079-06-06" /><PARAM ID="1524727758" OBJECTID="37020216" CHANGEID="600745658" CHANGEIDEND="0" TYPEID="8" VALUE="68:13:1601003:381" UPDATEDATE="2024-09-09" STARTDATE="2024-09-09" ENDDATE="2079-06-06" /><PARAM ID="1524727807" OBJECTID="66820337" CHANGEID="600745694" CHANGEIDEND="0" TYPEID="8" VALUE="68:13:0801009:168" UPDATEDATE="2024-09-09" STARTDATE="2024-09-09" ENDDATE="2079-06-06" /><PARAM ID="1524727808" OBJECTID="66820337" CHANGEID="600745694" CHANGEIDEND="0" TYPEID="13" VALUE="686244401010000002040029000000010" UPDATEDATE="2024-09-09" STARTDATE="2024-09-09" ENDDATE="2079-06-06" /><PARAM ID="1524742233" OBJECTID="81812395" CHANGEID="600748792" CHANGEIDEND="0" TYPEID="8" VALUE="68:25:0000005:235" UPDATEDATE="2024-09-09" STARTDATE="2024-09-09" ENDDATE="2079-06-06" /><PARAM ID="1524742234" OBJECTID="81810877" CHANGEID="600748793" CHANGEIDEND="0" TYPEID="8" VALUE="68:25:0000005:233" UPDATEDATE="2024-09-09" STARTDATE="2024-09-09" ENDDATE="2079-06-06" /><PARAM ID="1524742235" OBJECTID="81808736" CHANGEID="600748794" CHANGEIDEND="0" TYPEID="8" VALUE="68:25:0000005:217" UPDATEDATE="2024-09-09" STARTDATE="2024-09-09" ENDDATE="2079-06-06" /><PARAM ID="1524742275" OBJECTID="81747050" CHANGEID="600748810" CHANGEIDEND="0" TYPEID="8" VALUE="68:25:0000005:1385" UPDATEDATE="2024-09-09" STARTDATE="2024-09-09" ENDDATE="2079-06-06" /><PARAM ID="1524742276" OBJECTID="81746061" CHANGEID="600748811" CHANGEIDEND="0" TYPEID="8" VALUE="68:25:0000005:1374" UPDATEDATE="2024-09-09" STARTDATE="2024-09-09" ENDDATE="2079-06-06" /><PARAM ID="1524742277" OBJECTID="81742213" CHANGEID="600748812" CHANGEIDEND="0" TYPEID="8" VALUE="68:25:0000005:1381" UPDATEDATE="2024-09-09" STARTDATE="2024-09-09" ENDDATE="2079-06-06" /><PARAM ID="1524742278" OBJECTID="81741930" CHANGEID="600748813" CHANGEIDEND="0" TYPEID="8" VALUE="68:25:0000005:1101" UPDATEDATE="2024-09-09" STARTDATE="2024-09-09" ENDDATE="2079-06-06" /><PARAM ID="1524742279" OBJECTID="81741923" CHANGEID="600748814" CHANGEIDEND="0" TYPEID="8" VALUE="68:25:0000005:1382" UPDATEDATE="2024-09-09" STARTDATE="2024-09-09" ENDDATE="2079-06-06" /><PARAM ID="1524742280" OBJECTID="81741683" CHANGEID="600748815" CHANGEIDEND="0" TYPEID="8" VALUE="68:25:0000005:1380" UPDATEDATE="2024-09-09" STARTDATE="2024-09-09" ENDDATE="2079-06-06" /><PARAM ID="1524742281" OBJECTID="81741372" CHANGEID="600748816" CHANGEIDEND="0" TYPEID="8" VALUE="68:25:0000005:1378" UPDATEDATE="2024-09-09" STARTDATE="2024-09-09" ENDDATE="2079-06-06" /><PARAM ID="1524742282" OBJECTID="81741187" CHANGEID="600748817" CHANGEIDEND="0" TYPEID="8" VALUE="68:25:0000005:1383" UPDATEDATE="2024-09-09" STARTDATE="2024-09-09" ENDDATE="2079-06-06" /><PARAM ID="1524742288" OBJECTID="81792896" CHANGEID="600748821" CHANGEIDEND="0" TYPEID="8" VALUE="68:25:0000005:1370" UPDATEDATE="2024-09-09" STARTDATE="2024-09-09" ENDDATE="2079-06-06" /><PARAM ID="1524742289" OBJECTID="81800459" CHANGEID="600748822" CHANGEIDEND="0" TYPEID="8" VALUE="68:25:0000005:1362" UPDATEDATE="2024-09-09" STARTDATE="2024-09-09" ENDDATE="2079-06-06" /><PARAM ID="1524742290" OBJECTID="81799339" CHANGEID="600748823" CHANGEIDEND="0" TYPEID="8" VALUE="68:25:0000005:1368" UPDATEDATE="2024-09-09" STARTDATE="2024-09-09" ENDDATE="2079-06-06" /><PARAM ID="1524742291" OBJECTID="81794839" CHANGEID="600748824" CHANGEIDEND="0" TYPEID="8" VALUE="68:25:0000005:1359" UPDATEDATE="2024-09-09" STARTDATE="2024-09-09" ENDDATE="2079-06-06" /><PARAM ID="1524756542" OBJECTID="79811575" CHANGEID="600751345" CHANGEIDEND="0" TYPEID="8" VALUE="68:07:0801003:257" UPDATEDATE="2024-09-09" STARTDATE="2024-09-09" ENDDATE="2079-06-06" /><PARAM ID="1524765117" OBJECTID="81756958" CHANGEID="600753192" CHANGEIDEND="0" TYPEID="8" VALUE="68:25:0000005:252" UPDATEDATE="2024-09-09" STARTDATE="2024-09-09" ENDDATE="2079-06-06" /><PARAM ID="1524862529" OBJECTID="69623185" CHANGEID="600774845" CHANGEIDEND="0" TYPEID="8" VALUE="68:01:0705003:1080" UPDATEDATE="2024-09-09" STARTDATE="2024-09-09" ENDDATE="2079-06-06" /><PARAM ID="1524862746" OBJECTID="69521960" CHANGEID="600774881" CHANGEIDEND="0" TYPEID="8" VALUE="68:01:0705003:884" UPDATEDATE="2024-09-09" STARTDATE="2024-09-09" ENDDATE="2079-06-06" /><PARAM ID="1524863153" OBJECTID="64665353" CHANGEID="600774960" CHANGEIDEND="0" TYPEID="8" VALUE="68:04:0000000:514" UPDATEDATE="2024-09-09" STARTDATE="2024-09-09" ENDDATE="2079-06-06" /><PARAM ID="1524863319" OBJECTID="10923885" CHANGEID="600774998" CHANGEIDEND="0" TYPEID="8" VALUE="68:01:0705003:1665" UPDATEDATE="2024-09-09" STARTDATE="2024-09-09" ENDDATE="2079-06-06" /><PARAM ID="1524863417" OBJECTID="5707737" CHANGEID="600775021" CHANGEIDEND="0" TYPEID="8" VALUE="68:19:0901007:743" UPDATEDATE="2024-09-09" STARTDATE="2024-09-09" ENDDATE="2079-06-06" /><PARAM ID="1524863505" OBJECTID="10924699" CHANGEID="600775038" CHANGEIDEND="0" TYPEID="8" VALUE="68:01:0705003:1666" UPDATEDATE="2024-09-09" STARTDATE="2024-09-09" ENDDATE="2079-06-06" /><PARAM ID="1524863745" OBJECTID="10918159" CHANGEID="600775080" CHANGEIDEND="0" TYPEID="8" VALUE="68:01:0705003:1022" UPDATEDATE="2024-09-09" STARTDATE="2024-09-09" ENDDATE="2079-06-06" /><PARAM ID="1524863875" OBJECTID="5707877" CHANGEID="600775104" CHANGEIDEND="0" TYPEID="8" VALUE="68:19:0901007:592" UPDATEDATE="2024-09-09" STARTDATE="2024-09-09" ENDDATE="2079-06-06" /><PARAM ID="1524863958" OBJECTID="16507789" CHANGEID="600775120" CHANGEIDEND="0" TYPEID="8" VALUE="68:04:1101006:1001" UPDATEDATE="2024-09-09" STARTDATE="2024-09-09" ENDDATE="2079-06-06" /><PARAM ID="1524864126" OBJECTID="16429857" CHANGEID="600775182" CHANGEIDEND="0" TYPEID="8" VALUE="68:04:1101006:1062" UPDATEDATE="2024-09-09" STARTDATE="2024-09-09" ENDDATE="2079-06-06" /><PARAM ID="1524864273" OBJECTID="14823903" CHANGEID="600775215" CHANGEIDEND="0" TYPEID="8" VALUE="68:19:0901018:426" UPDATEDATE="2024-09-09" STARTDATE="2024-09-09" ENDDATE="2079-06-06" /><PARAM ID="1524864358" OBJECTID="16760330" CHANGEID="600775238" CHANGEIDEND="0" TYPEID="8" VALUE="68:19:0901006:867" UPDATEDATE="2024-09-09" STARTDATE="2024-09-09" ENDDATE="2079-06-06" /><PARAM ID="1524865076" OBJECTID="31551609" CHANGEID="600775419" CHANGEIDEND="0" TYPEID="8" VALUE="68:19:0901018:383" UPDATEDATE="2024-09-09" STARTDATE="2024-09-09" ENDDATE="2079-06-06" /><PARAM ID="1524869697" OBJECTID="36343461" CHANGEID="600776510" CHANGEIDEND="0" TYPEID="8" VALUE="68:19:0901015:248" UPDATEDATE="2024-09-09" STARTDATE="2024-09-09" ENDDATE="2079-06-06" /><PARAM ID="1524869766" OBJECTID="36412685" CHANGEID="600776526" CHANGEIDEND="0" TYPEID="8" VALUE="68:19:0901015:329" UPDATEDATE="2024-09-09" STARTDATE="2024-09-09" ENDDATE="2079-06-06" /><PARAM ID="1524869978" OBJECTID="16444531" CHANGEID="600776574" CHANGEIDEND="0" TYPEID="8" VALUE="68:04:1101006:977" UPDATEDATE="2024-09-09" STARTDATE="2024-09-09" ENDDATE="2079-06-06" /><PARAM ID="1524869958" OBJECTID="37316730" CHANGEID="600776559" CHANGEIDEND="0" TYPEID="8" VALUE="68:19:0901005:320" UPDATEDATE="2024-09-09" STARTDATE="2024-09-09" ENDDATE="2079-06-06" /><PARAM ID="1524870008" OBJECTID="37323881" CHANGEID="600776580" CHANGEIDEND="0" TYPEID="8" VALUE="68:19:0901005:338" UPDATEDATE="2024-09-09" STARTDATE="2024-09-09" ENDDATE="2079-06-06" /><PARAM ID="1524870088" OBJECTID="16378986" CHANGEID="600776598" CHANGEIDEND="0" TYPEID="8" VALUE="68:04:1101006:1134" UPDATEDATE="2024-09-09" STARTDATE="2024-09-09" ENDDATE="2079-06-06" /><PARAM ID="1524870199" OBJECTID="16417653" CHANGEID="600776622" CHANGEIDEND="0" TYPEID="8" VALUE="68:04:1101006:961" UPDATEDATE="2024-09-09" STARTDATE="2024-09-09" ENDDATE="2079-06-06" /><PARAM ID="1524870370" OBJECTID="16451898" CHANGEID="600776674" CHANGEIDEND="0" TYPEID="8" VALUE="68:04:1101006:937" UPDATEDATE="2024-09-09" STARTDATE="2024-09-09" ENDDATE="2079-06-06" /><PARAM ID="1524870445" OBJECTID="44812153" CHANGEID="600776690" CHANGEIDEND="0" TYPEID="8" VALUE="68:19:0901021:620" UPDATEDATE="2024-09-09" STARTDATE="2024-09-09" ENDDATE="2079-06-06" /><PARAM ID="1524870645" OBJECTID="44813740" CHANGEID="600776730" CHANGEIDEND="0" TYPEID="8" VALUE="68:19:0901021:1067" UPDATEDATE="2024-09-09" STARTDATE="2024-09-09" ENDDATE="2079-06-06" /><PARAM ID="1524870737" OBJECTID="16954316" CHANGEID="600776758" CHANGEIDEND="0" TYPEID="8" VALUE="68:04:1101006:1174" UPDATEDATE="2024-09-09" STARTDATE="2024-09-09" ENDDATE="2079-06-06" /><PARAM ID="1524870610" OBJECTID="16973372" CHANGEID="600776725" CHANGEIDEND="0" TYPEID="8" VALUE="68:01:0705003:1533" UPDATEDATE="2024-09-09" STARTDATE="2024-09-09" ENDDATE="2079-06-06" /><PARAM ID="1524870724" OBJECTID="46841191" CHANGEID="600776755" CHANGEIDEND="0" TYPEID="8" VALUE="68:19:0901007:495" UPDATEDATE="2024-09-09" STARTDATE="2024-09-09" ENDDATE="2079-06-06" /><PARAM ID="1524870786" OBJECTID="46861047" CHANGEID="600776770" CHANGEIDEND="0" TYPEID="8" VALUE="68:19:0901007:498" UPDATEDATE="2024-09-09" STARTDATE="2024-09-09" ENDDATE="2079-06-06" /><PARAM ID="1524870861" OBJECTID="57802009" CHANGEID="600776799" CHANGEIDEND="0" TYPEID="8" VALUE="68:04:1101008:529" UPDATEDATE="2024-09-09" STARTDATE="2024-09-09" ENDDATE="2079-06-06" /><PARAM ID="1524870998" OBJECTID="57807670" CHANGEID="600776882" CHANGEIDEND="0" TYPEID="8" VALUE="68:04:1101008:532" UPDATEDATE="2024-09-09" STARTDATE="2024-09-09" ENDDATE="2079-06-06" /><PARAM ID="1524871123" OBJECTID="38702020" CHANGEID="600776909" CHANGEIDEND="0" TYPEID="8" VALUE="68:01:0705003:1544" UPDATEDATE="2024-09-09" STARTDATE="2024-09-09" ENDDATE="2079-06-06" /><PARAM ID="1524871778" OBJECTID="70091666" CHANGEID="600777035" CHANGEIDEND="0" TYPEID="8" VALUE="68:19:0901002:181" UPDATEDATE="2024-09-09" STARTDATE="2024-09-09" ENDDATE="2079-06-06" /><PARAM ID="1524872032" OBJECTID="47884630" CHANGEID="600777107" CHANGEIDEND="0" TYPEID="8" VALUE="68:01:0705003:1724" UPDATEDATE="2024-09-09" STARTDATE="2024-09-09" ENDDATE="2079-06-06" /><PARAM ID="1524907562" OBJECTID="95896688" CHANGEID="600784989" CHANGEIDEND="0" TYPEID="8" VALUE="68:19:0901007:563" UPDATEDATE="2024-09-09" STARTDATE="2024-09-09" ENDDATE="2079-06-06" /><PARAM ID="1524907426" OBJECTID="80694212" CHANGEID="600784967" CHANGEIDEND="0" TYPEID="8" VALUE="68:19:0901003:680" UPDATEDATE="2024-09-09" STARTDATE="2024-09-09" ENDDATE="2079-06-06" /><PARAM ID="1524907604" OBJECTID="161309851" CHANGEID="600785002" CHANGEIDEND="0" TYPEID="8" VALUE="68:19:0901021:526" UPDATEDATE="2024-09-09" STARTDATE="2024-09-09" ENDDATE="2079-06-06" /><PARAM ID="1524908378" OBJECTID="16748807" CHANGEID="600785108" CHANGEIDEND="0" TYPEID="8" VALUE="68:19:0901006:878" UPDATEDATE="2024-09-09" STARTDATE="2024-09-09" ENDDATE="2079-06-06" /><PARAM ID="1524924093" OBJECTID="76272405" CHANGEID="600788778" CHANGEIDEND="0" TYPEID="8" VALUE="68:10:0600045:99" UPDATEDATE="2024-09-09" STARTDATE="2024-09-09" ENDDATE="2079-06-06" /><PARAM ID="1524924981" OBJECTID="165149052" CHANGEID="600788917" CHANGEIDEND="0" TYPEID="8" VALUE="68:03:1501097:355" UPDATEDATE="2024-09-09" STARTDATE="2024-09-09" ENDDATE="2079-06-06" /><PARAM ID="1524924982" OBJECTID="165149052" CHANGEID="600788917" CHANGEIDEND="0" TYPEID="15" VALUE="1" UPDATEDATE="2024-09-09" STARTDATE="2024-09-09" ENDDATE="2079-06-06" /><PARAM ID="1524924983" OBJECTID="165149052" CHANGEID="600788917" CHANGEIDEND="0" TYPEID="13" VALUE="686041010010000002440011000100000" UPDATEDATE="2024-09-09" STARTDATE="2024-09-09" ENDDATE="2079-06-06" /><PARAM ID="1524925422" OBJECTID="26925852" CHANGEID="600789011" CHANGEIDEND="0" TYPEID="8" VALUE="68:10:0600045:97" UPDATEDATE="2024-09-09" STARTDATE="2024-09-09" ENDDATE="2079-06-06" /><PARAM ID="1524926233" OBJECTID="7425717" CHANGEID="600789246" CHANGEIDEND="0" TYPEID="8" VALUE="68:10:0600049:60" UPDATEDATE="2024-09-09" STARTDATE="2024-09-09" ENDDATE="2079-06-06" /><PARAM ID="1524927740" OBJECTID="7425553" CHANGEID="600789663" CHANGEIDEND="0" TYPEID="8" VALUE="68:10:0600049:61" UPDATEDATE="2024-09-09" STARTDATE="2024-09-09" ENDDATE="2079-06-06" /><PARAM ID="1524929218" OBJECTID="46660055" CHANGEID="600789971" CHANGEIDEND="0" TYPEID="8" VALUE="68:10:0800031:73" UPDATEDATE="2024-09-09" STARTDATE="2024-09-09" ENDDATE="2079-06-06" /><PARAM ID="1524929456" OBJECTID="46660272" CHANGEID="600790021" CHANGEIDEND="0" TYPEID="8" VALUE="68:10:0800031:74" UPDATEDATE="2024-09-09" STARTDATE="2024-09-09" ENDDATE="2079-06-06" /><PARAM ID="1524929786" OBJECTID="46714763" CHANGEID="600790084" CHANGEIDEND="0" TYPEID="8" VALUE="68:10:0800030:42" UPDATEDATE="2024-09-09" STARTDATE="2024-09-09" ENDDATE="2079-06-06" /><PARAM ID="1524930195" OBJECTID="46714476" CHANGEID="600790197" CHANGEIDEND="0" TYPEID="8" VALUE="68:10:0800030:43" UPDATEDATE="2024-09-09" STARTDATE="2024-09-09" ENDDATE="2079-06-06" /><PARAM ID="1524930472" OBJECTID="67131420" CHANGEID="600790291" CHANGEIDEND="0" TYPEID="8" VALUE="68:10:0800030:40" UPDATEDATE="2024-09-09" STARTDATE="2024-09-09" ENDDATE="2079-06-06" /><PARAM ID="1524930761" OBJECTID="67153162" CHANGEID="600790359" CHANGEIDEND="0" TYPEID="8" VALUE="68:10:0800033:67" UPDATEDATE="2024-09-09" STARTDATE="2024-09-09" ENDDATE="2079-06-06" /><PARAM ID="1524979659" OBJECTID="17869172" CHANGEID="600806758" CHANGEIDEND="0" TYPEID="8" VALUE="68:10:0500020:38" UPDATEDATE="2024-09-10" STARTDATE="2024-09-10" ENDDATE="2079-06-06" /><PARAM ID="1524989697" OBJECTID="55723495" CHANGEID="600808893" CHANGEIDEND="0" TYPEID="8" VALUE="68:19:0603003:160" UPDATEDATE="2024-09-10" STARTDATE="2024-09-10" ENDDATE="2079-06-06" /><PARAM ID="1525090397" OBJECTID="38908186" CHANGEID="600828852" CHANGEIDEND="0" TYPEID="8" VALUE="68:07:0203001:102" UPDATEDATE="2024-09-10" STARTDATE="2024-09-10" ENDDATE="2079-06-06" /><PARAM ID="1525090406" OBJECTID="165171673" CHANGEID="600828858" CHANGEIDEND="0" TYPEID="8" VALUE="68:07:1401003:155" UPDATEDATE="2024-09-10" STARTDATE="2024-09-10" ENDDATE="2079-06-06" /><PARAM ID="1525090407" OBJECTID="165171673" CHANGEID="600828858" CHANGEIDEND="0" TYPEID="15" VALUE="1" UPDATEDATE="2024-09-10" STARTDATE="2024-09-10" ENDDATE="2079-06-06" /><PARAM ID="1525090408" OBJECTID="165171673" CHANGEID="600828858" CHANGEIDEND="0" TYPEID="13" VALUE="686124701010000001140056000100000" UPDATEDATE="2024-09-10" STARTDATE="2024-09-10" ENDDATE="2079-06-06" /><PARAM ID="1525090738" OBJECTID="165171707" CHANGEID="600828930" CHANGEIDEND="0" TYPEID="8" VALUE="68:07:1401003:180" UPDATEDATE="2024-09-10" STARTDATE="2024-09-10" ENDDATE="2079-06-06" /><PARAM ID="1525090739" OBJECTID="165171707" CHANGEID="600828930" CHANGEIDEND="0" TYPEID="15" VALUE="2" UPDATEDATE="2024-09-10" STARTDATE="2024-09-10" ENDDATE="2079-06-06" /><PARAM ID="1525090740" OBJECTID="165171707" CHANGEID="600828930" CHANGEIDEND="0" TYPEID="13" VALUE="686124701010000001140056000200000" UPDATEDATE="2024-09-10" STARTDATE="2024-09-10" ENDDATE="2079-06-06" /><PARAM ID="1525091403" OBJECTID="38870299" CHANGEID="600829036" CHANGEIDEND="0" TYPEID="8" VALUE="68:07:0203001:107" UPDATEDATE="2024-09-10" STARTDATE="2024-09-10" ENDDATE="2079-06-06" /><PARAM ID="1525091579" OBJECTID="38870716" CHANGEID="600829065" CHANGEIDEND="0" TYPEID="8" VALUE="68:07:0203001:113" UPDATEDATE="2024-09-10" STARTDATE="2024-09-10" ENDDATE="2079-06-06" /><PARAM ID="1525091680" OBJECTID="38944996" CHANGEID="600829095" CHANGEIDEND="0" TYPEID="8" VALUE="68:07:0203001:84" UPDATEDATE="2024-09-10" STARTDATE="2024-09-10" ENDDATE="2079-06-06" /><PARAM ID="1525091750" OBJECTID="38944966" CHANGEID="600829114" CHANGEIDEND="0" TYPEID="8" VALUE="68:07:0203001:85" UPDATEDATE="2024-09-10" STARTDATE="2024-09-10" ENDDATE="2079-06-06" /><PARAM ID="1525096172" OBJECTID="25767383" CHANGEID="600830146" CHANGEIDEND="0" TYPEID="8" VALUE="68:07:1401002:224" UPDATEDATE="2024-09-10" STARTDATE="2024-09-10" ENDDATE="2079-06-06" /><PARAM ID="1525096337" OBJECTID="165172351" CHANGEID="600830189" CHANGEIDEND="0" TYPEID="8" VALUE="68:11:1101008:275" UPDATEDATE="2024-09-10" STARTDATE="2024-09-10" ENDDATE="2079-06-06" /><PARAM ID="1525096338" OBJECTID="165172351" CHANGEID="600830189" CHANGEIDEND="0" TYPEID="15" VALUE="2" UPDATEDATE="2024-09-10" STARTDATE="2024-09-10" ENDDATE="2079-06-06" /><PARAM ID="1525096339" OBJECTID="165172351" CHANGEID="600830189" CHANGEIDEND="0" TYPEID="13" VALUE="686201510510000004940544000200000" UPDATEDATE="2024-09-10" STARTDATE="2024-09-10" ENDDATE="2079-06-06" /><PARAM ID="1525125062" OBJECTID="165176641" CHANGEID="600836805" CHANGEIDEND="0" TYPEID="8" VALUE="68:07:1401002:186" UPDATEDATE="2024-09-10" STARTDATE="2024-09-10" ENDDATE="2079-06-06" /><PARAM ID="1525125063" OBJECTID="165176641" CHANGEID="600836805" CHANGEIDEND="0" TYPEID="15" VALUE="1" UPDATEDATE="2024-09-10" STARTDATE="2024-09-10" ENDDATE="2079-06-06" /><PARAM ID="1525125064" OBJECTID="165176641" CHANGEID="600836805" CHANGEIDEND="0" TYPEID="13" VALUE="686124701010000000240082000100000" UPDATEDATE="2024-09-10" STARTDATE="2024-09-10" ENDDATE="2079-06-06" /><PARAM ID="1525125250" OBJECTID="165176671" CHANGEID="600836851" CHANGEIDEND="0" TYPEID="8" VALUE="68:07:1401002:187" UPDATEDATE="2024-09-10" STARTDATE="2024-09-10" ENDDATE="2079-06-06" /><PARAM ID="1525125251" OBJECTID="165176671" CHANGEID="600836851" CHANGEIDEND="0" TYPEID="15" VALUE="2" UPDATEDATE="2024-09-10" STARTDATE="2024-09-10" ENDDATE="2079-06-06" /><PARAM ID="1525125252" OBJECTID="165176671" CHANGEID="600836851" CHANGEIDEND="0" TYPEID="13" VALUE="686124701010000000240082000200000" UPDATEDATE="2024-09-10" STARTDATE="2024-09-10" ENDDATE="2079-06-06" /><PARAM ID="1525146587" OBJECTID="79239939" CHANGEID="600841074" CHANGEIDEND="0" TYPEID="8" VALUE="68:07:1402002:259" UPDATEDATE="2024-09-10" STARTDATE="2024-09-10" ENDDATE="2079-06-06" /><PARAM ID="1525146588" OBJECTID="79239939" CHANGEID="600841074" CHANGEIDEND="0" TYPEID="13" VALUE="686124701060000000140103000000010" UPDATEDATE="2024-09-10" STARTDATE="2024-09-10" ENDDATE="2079-06-06" /><PARAM ID="1525146891" OBJECTID="79239909" CHANGEID="600841150" CHANGEIDEND="0" TYPEID="8" VALUE="68:07:1402002:258" UPDATEDATE="2024-09-10" STARTDATE="2024-09-10" ENDDATE="2079-06-06" /><PARAM ID="1525146892" OBJECTID="79239909" CHANGEID="600841150" CHANGEIDEND="0" TYPEID="13" VALUE="686124701060000000140103000000010" UPDATEDATE="2024-09-10" STARTDATE="2024-09-10" ENDDATE="2079-06-06" /><PARAM ID="1525149350" OBJECTID="11993130" CHANGEID="600841734" CHANGEIDEND="0" TYPEID="8" VALUE="68:11:0501012:42" UPDATEDATE="2024-09-10" STARTDATE="2024-09-10" ENDDATE="2079-06-06" /><PARAM ID="1525149454" OBJECTID="11987146" CHANGEID="600841757" CHANGEIDEND="0" TYPEID="8" VALUE="68:11:0501012:154" UPDATEDATE="2024-09-10" STARTDATE="2024-09-10" ENDDATE="2079-06-06" /><PARAM ID="1525149567" OBJECTID="39957918" CHANGEID="600841788" CHANGEIDEND="0" TYPEID="8" VALUE="68:11:0501013:155" UPDATEDATE="2024-09-10" STARTDATE="2024-09-10" ENDDATE="2079-06-06" /><PARAM ID="1525149678" OBJECTID="39940050" CHANGEID="600841806" CHANGEIDEND="0" TYPEID="8" VALUE="68:11:0501020:138" UPDATEDATE="2024-09-10" STARTDATE="2024-09-10" ENDDATE="2079-06-06" /><PARAM ID="1525155261" OBJECTID="33921373" CHANGEID="600843236" CHANGEIDEND="0" TYPEID="8" VALUE="68:07:1402003:167" UPDATEDATE="2024-09-10" STARTDATE="2024-09-10" ENDDATE="2079-06-06" /><PARAM ID="1351264999" OBJECTID="65420768" CHANGEID="480437702" CHANGEIDEND="600843500" TYPEID="8" VALUE="68:12:0601002:210" UPDATEDATE="2024-09-10" STARTDATE="2022-11-24" ENDDATE="2024-09-10" /><PARAM ID="1525156354" OBJECTID="19370177" CHANGEID="600843508" CHANGEIDEND="0" TYPEID="20" VALUE="04.03.2024" UPDATEDATE="2024-09-10" STARTDATE="2024-09-10" ENDDATE="2079-06-06" /><PARAM ID="1525156499" OBJECTID="19368295" CHANGEID="600843551" CHANGEIDEND="0" TYPEID="20" VALUE="06.03.2024" UPDATEDATE="2024-09-10" STARTDATE="2024-09-10" ENDDATE="2079-06-06" /><PARAM ID="1525165183" OBJECTID="165181682" CHANGEID="600845525" CHANGEIDEND="0" TYPEID="8" VALUE="68:20:2102011:229" UPDATEDATE="2024-09-10" STARTDATE="2024-09-10" ENDDATE="2079-06-06" /><PARAM ID="1525165184" OBJECTID="165181682" CHANGEID="600845525" CHANGEIDEND="0" TYPEID="15" VALUE="1" UPDATEDATE="2024-09-10" STARTDATE="2024-09-10" ENDDATE="2079-06-06" /><PARAM ID="1525165185" OBJECTID="165181682" CHANGEID="600845525" CHANGEIDEND="0" TYPEID="13" VALUE="686404771060000000540077000100000" UPDATEDATE="2024-09-10" STARTDATE="2024-09-10" ENDDATE="2079-06-06" /><PARAM ID="1525171012" OBJECTID="76108858" CHANGEID="600847100" CHANGEIDEND="0" TYPEID="8" VALUE="68:02:1204005:199" UPDATEDATE="2024-09-10" STARTDATE="2024-09-10" ENDDATE="2079-06-06" /><PARAM ID="1525241763" OBJECTID="2454262" CHANGEID="600882340" CHANGEIDEND="0" TYPEID="8" VALUE="68:06:0506001:280" UPDATEDATE="2024-09-11" STARTDATE="2024-09-11" ENDDATE="2079-06-06" /><PARAM ID="1525241938" OBJECTID="55721196" CHANGEID="600882389" CHANGEIDEND="0" TYPEID="8" VALUE="68:19:0603003:156" UPDATEDATE="2024-09-11" STARTDATE="2024-09-11" ENDDATE="2079-06-06" /><PARAM ID="1525241949" OBJECTID="46743766" CHANGEID="600882391" CHANGEIDEND="0" TYPEID="8" VALUE="68:12:0601003:297" UPDATEDATE="2024-09-11" STARTDATE="2024-09-11" ENDDATE="2079-06-06" /><PARAM ID="1525241950" OBJECTID="2454585" CHANGEID="600882392" CHANGEIDEND="0" TYPEID="8" VALUE="68:06:0506001:253" UPDATEDATE="2024-09-11" STARTDATE="2024-09-11" ENDDATE="2079-06-06" /><PARAM ID="1525242142" OBJECTID="2454848" CHANGEID="600882425" CHANGEIDEND="0" TYPEID="8" VALUE="68:06:0506001:463" UPDATEDATE="2024-09-11" STARTDATE="2024-09-11" ENDDATE="2079-06-06" /><PARAM ID="1525242234" OBJECTID="2454856" CHANGEID="600882450" CHANGEIDEND="0" TYPEID="8" VALUE="68:06:0506001:462" UPDATEDATE="2024-09-11" STARTDATE="2024-09-11" ENDDATE="2079-06-06" /><PARAM ID="1525242220" OBJECTID="65414611" CHANGEID="600882447" CHANGEIDEND="0" TYPEID="8" VALUE="68:12:0601002:210" UPDATEDATE="2024-09-11" STARTDATE="2024-09-11" ENDDATE="2079-06-06" /><PARAM ID="1525242375" OBJECTID="2456432" CHANGEID="600882474" CHANGEIDEND="0" TYPEID="8" VALUE="68:06:0506001:472" UPDATEDATE="2024-09-11" STARTDATE="2024-09-11" ENDDATE="2079-06-06" /><PARAM ID="1525242452" OBJECTID="2456694" CHANGEID="600882491" CHANGEIDEND="0" TYPEID="8" VALUE="68:06:0506001:247" UPDATEDATE="2024-09-11" STARTDATE="2024-09-11" ENDDATE="2079-06-06" /><PARAM ID="1525242664" OBJECTID="2457989" CHANGEID="600882542" CHANGEIDEND="0" TYPEID="8" VALUE="68:06:0506001:267" UPDATEDATE="2024-09-11" STARTDATE="2024-09-11" ENDDATE="2079-06-06" /><PARAM ID="1525242890" OBJECTID="2458068" CHANGEID="600882575" CHANGEIDEND="0" TYPEID="8" VALUE="68:06:0506001:261" UPDATEDATE="2024-09-11" STARTDATE="2024-09-11" ENDDATE="2079-06-06" /><PARAM ID="1525243446" OBJECTID="76990832" CHANGEID="600882741" CHANGEIDEND="0" TYPEID="8" VALUE="68:06:0506001:299" UPDATEDATE="2024-09-11" STARTDATE="2024-09-11" ENDDATE="2079-06-06" /><PARAM ID="1525243381" OBJECTID="76986590" CHANGEID="600882726" CHANGEIDEND="0" TYPEID="8" VALUE="68:06:0506001:468" UPDATEDATE="2024-09-11" STARTDATE="2024-09-11" ENDDATE="2079-06-06" /><PARAM ID="1525243589" OBJECTID="15411189" CHANGEID="600882779" CHANGEIDEND="0" TYPEID="8" VALUE="68:06:0505003:349" UPDATEDATE="2024-09-11" STARTDATE="2024-09-11" ENDDATE="2079-06-06" /><PARAM ID="1525253095" OBJECTID="15421895" CHANGEID="600885068" CHANGEIDEND="0" TYPEID="8" VALUE="68:06:0505003:194" UPDATEDATE="2024-09-11" STARTDATE="2024-09-11" ENDDATE="2079-06-06" /><PARAM ID="1525253131" OBJECTID="15442164" CHANGEID="600885079" CHANGEIDEND="0" TYPEID="8" VALUE="68:06:0000000:1350" UPDATEDATE="2024-09-11" STARTDATE="2024-09-11" ENDDATE="2079-06-06" /><PARAM ID="1525253171" OBJECTID="44085452" CHANGEID="600885093" CHANGEIDEND="0" TYPEID="8" VALUE="68:06:0505003:350" UPDATEDATE="2024-09-11" STARTDATE="2024-09-11" ENDDATE="2079-06-06" /><PARAM ID="1525253880" OBJECTID="44087486" CHANGEID="600885429" CHANGEIDEND="0" TYPEID="8" VALUE="68:06:0505003:200" UPDATEDATE="2024-09-11" STARTDATE="2024-09-11" ENDDATE="2079-06-06" /><PARAM ID="1525254138" OBJECTID="55746292" CHANGEID="600885506" CHANGEIDEND="0" TYPEID="8" VALUE="68:06:0502001:99" UPDATEDATE="2024-09-11" STARTDATE="2024-09-11" ENDDATE="2079-06-06" /><PARAM ID="1525253953" OBJECTID="44091625" CHANGEID="600885457" CHANGEIDEND="0" TYPEID="8" VALUE="68:06:0505003:203" UPDATEDATE="2024-09-11" STARTDATE="2024-09-11" ENDDATE="2079-06-06" /><PARAM ID="1525254026" OBJECTID="44091670" CHANGEID="600885468" CHANGEIDEND="0" TYPEID="8" VALUE="68:06:0505003:204" UPDATEDATE="2024-09-11" STARTDATE="2024-09-11" ENDDATE="2079-06-06" /><PARAM ID="1525254270" OBJECTID="56287470" CHANGEID="600885536" CHANGEIDEND="0" TYPEID="8" VALUE="68:06:0502001:104" UPDATEDATE="2024-09-11" STARTDATE="2024-09-11" ENDDATE="2079-06-06" /><PARAM ID="1525254395" OBJECTID="58621767" CHANGEID="600885577" CHANGEIDEND="0" TYPEID="8" VALUE="68:06:0503001:126" UPDATEDATE="2024-09-11" STARTDATE="2024-09-11" ENDDATE="2079-06-06" /><PARAM ID="1525268912" OBJECTID="165195264" CHANGEID="600890039" CHANGEIDEND="0" TYPEID="8" VALUE="68:29:0308061:1357" UPDATEDATE="2024-09-11" STARTDATE="2024-09-11" ENDDATE="2079-06-06" /><PARAM ID="1525268913" OBJECTID="165195264" CHANGEID="600890039" CHANGEIDEND="0" TYPEID="15" VALUE="1" UPDATEDATE="2024-09-11" STARTDATE="2024-09-11" ENDDATE="2079-06-06" /><PARAM ID="1525268914" OBJECTID="165195264" CHANGEID="600890039" CHANGEIDEND="0" TYPEID="13" VALUE="687010000010000027140004000100000" UPDATEDATE="2024-09-11" STARTDATE="2024-09-11" ENDDATE="2079-06-06" /><PARAM ID="1525269120" OBJECTID="49534741" CHANGEID="600890094" CHANGEIDEND="0" TYPEID="8" VALUE="68:09:1702003:171" UPDATEDATE="2024-09-11" STARTDATE="2024-09-11" ENDDATE="2079-06-06" /><PARAM ID="1525308814" OBJECTID="27701959" CHANGEID="600900421" CHANGEIDEND="0" TYPEID="8" VALUE="68:02:1204005:351" UPDATEDATE="2024-09-11" STARTDATE="2024-09-11" ENDDATE="2079-06-06" /><PARAM ID="1488814728" OBJECTID="80498234" CHANGEID="577105020" CHANGEIDEND="600922889" TYPEID="8" VALUE="68:05:0705019:64" UPDATEDATE="2024-09-11" STARTDATE="2023-12-21" ENDDATE="2024-09-11" /><PARAM ID="1525428800" OBJECTID="68836914" CHANGEID="600925157" CHANGEIDEND="0" TYPEID="8" VALUE="68:05:0501009:65" UPDATEDATE="2024-09-11" STARTDATE="2024-09-11" ENDDATE="2079-06-06" /><PARAM ID="1525450220" OBJECTID="11303509" CHANGEID="600930518" CHANGEIDEND="0" TYPEID="8" VALUE="68:09:1702005:149" UPDATEDATE="2024-09-11" STARTDATE="2024-09-11" ENDDATE="2079-06-06" /><PARAM ID="1525451204" OBJECTID="11303609" CHANGEID="600930684" CHANGEIDEND="0" TYPEID="8" VALUE="68:09:1702005:142" UPDATEDATE="2024-09-11" STARTDATE="2024-09-11" ENDDATE="2079-06-06" /><PARAM ID="1525452655" OBJECTID="11334422" CHANGEID="600930934" CHANGEIDEND="0" TYPEID="8" VALUE="68:09:1702005:169" UPDATEDATE="2024-09-11" STARTDATE="2024-09-11" ENDDATE="2079-06-06" /><PARAM ID="1525452814" OBJECTID="11348692" CHANGEID="600931003" CHANGEIDEND="0" TYPEID="8" VALUE="68:09:1702005:136" UPDATEDATE="2024-09-11" STARTDATE="2024-09-11" ENDDATE="2079-06-06" /><PARAM ID="1525453427" OBJECTID="11334418" CHANGEID="600931128" CHANGEIDEND="0" TYPEID="8" VALUE="68:09:1702005:168" UPDATEDATE="2024-09-11" STARTDATE="2024-09-11" ENDDATE="2079-06-06" /><PARAM ID="1525453412" OBJECTID="13860526" CHANGEID="600931121" CHANGEIDEND="0" TYPEID="8" VALUE="68:09:1701001:206" UPDATEDATE="2024-09-11" STARTDATE="2024-09-11" ENDDATE="2079-06-06" /><PARAM ID="1525453787" OBJECTID="13860533" CHANGEID="600931181" CHANGEIDEND="0" TYPEID="8" VALUE="68:09:1701001:205" UPDATEDATE="2024-09-11" STARTDATE="2024-09-11" ENDDATE="2079-06-06" /><PARAM ID="1525454442" OBJECTID="81731837" CHANGEID="600931472" CHANGEIDEND="0" TYPEID="8" VALUE="68:09:1703001:99" UPDATEDATE="2024-09-11" STARTDATE="2024-09-11" ENDDATE="2079-06-06" /><PARAM ID="1525454569" OBJECTID="81732094" CHANGEID="600931496" CHANGEIDEND="0" TYPEID="8" VALUE="68:09:1703001:97" UPDATEDATE="2024-09-11" STARTDATE="2024-09-11" ENDDATE="2079-06-06" /><PARAM ID="1525455087" OBJECTID="81734093" CHANGEID="600931579" CHANGEIDEND="0" TYPEID="8" VALUE="68:09:1703001:101" UPDATEDATE="2024-09-11" STARTDATE="2024-09-11" ENDDATE="2079-06-06" /><PARAM ID="1525456979" OBJECTID="54638164" CHANGEID="600931906" CHANGEIDEND="0" TYPEID="8" VALUE="68:09:1706001:10" UPDATEDATE="2024-09-11" STARTDATE="2024-09-11" ENDDATE="2079-06-06" /><PARAM ID="1525456935" OBJECTID="81858751" CHANGEID="600931893" CHANGEIDEND="0" TYPEID="8" VALUE="68:09:1703001:90" UPDATEDATE="2024-09-11" STARTDATE="2024-09-11" ENDDATE="2079-06-06" /><PARAM ID="1525457392" OBJECTID="81861436" CHANGEID="600931976" CHANGEIDEND="0" TYPEID="8" VALUE="68:09:1703001:89" UPDATEDATE="2024-09-11" STARTDATE="2024-09-11" ENDDATE="2079-06-06" /><PARAM ID="1525457955" OBJECTID="54638070" CHANGEID="600932051" CHANGEIDEND="0" TYPEID="8" VALUE="68:09:1706001:11" UPDATEDATE="2024-09-11" STARTDATE="2024-09-11" ENDDATE="2079-06-06" /><PARAM ID="1525462097" OBJECTID="28196284" CHANGEID="600933067" CHANGEIDEND="0" TYPEID="8" VALUE="68:25:0000025:290" UPDATEDATE="2024-09-11" STARTDATE="2024-09-11" ENDDATE="2079-06-06" /><PARAM ID="1525462098" OBJECTID="28196202" CHANGEID="600933068" CHANGEIDEND="0" TYPEID="8" VALUE="68:25:0000025:285" UPDATEDATE="2024-09-11" STARTDATE="2024-09-11" ENDDATE="2079-06-06" /><PARAM ID="1525462099" OBJECTID="28195653" CHANGEID="600933069" CHANGEIDEND="0" TYPEID="8" VALUE="68:25:0000025:274" UPDATEDATE="2024-09-11" STARTDATE="2024-09-11" ENDDATE="2079-06-06" /><PARAM ID="1525462100" OBJECTID="28195458" CHANGEID="600933070" CHANGEIDEND="0" TYPEID="8" VALUE="68:25:0000025:260" UPDATEDATE="2024-09-11" STARTDATE="2024-09-11" ENDDATE="2079-06-06" /><PARAM ID="1525462268" OBJECTID="28289756" CHANGEID="600933122" CHANGEIDEND="0" TYPEID="8" VALUE="68:25:0000025:182" UPDATEDATE="2024-09-11" STARTDATE="2024-09-11" ENDDATE="2079-06-06" /></PARAMS>