<?xml version="1.0" encoding="utf-8"?><ITEMS><ITEM ID="235489875" OBJECTID="165064001" PARENTOBJID="106095" CHANGEID="600517221" OKTMO="26615450101" PREVID="0" NEXTID="0" UPDATEDATE="2024-09-05" STARTDATE="2024-09-05" ENDDATE="2079-06-06" ISACTIVE="1" PATH="103401.95232482.95232492.104416.106095.165064001" /><ITEM ID="235602283" OBJECTID="165170365" PARENTOBJID="105679" CHANGEID="600826872" OKTMO="26720000001" PREVID="0" NEXTID="0" UPDATEDATE="2024-09-10" STARTDATE="2024-09-10" ENDDATE="2079-06-06" ISACTIVE="1" PATH="103401.95232505.103550.105679.165170365" /><ITEM ID="235605347" OBJECTID="165173282" PARENTOBJID="105679" CHANGEID="600831847" OKTMO="26720000001" PREVID="0" NEXTID="0" UPDATEDATE="2024-09-10" STARTDATE="2024-09-10" ENDDATE="2079-06-06" ISACTIVE="1" PATH="103401.95232505.103550.105679.165173282" /><ITEM ID="235605493" OBJECTID="165173426" PARENTOBJID="103265" CHANGEID="600832210" OKTMO="26720000001" PREVID="0" NEXTID="0" UPDATEDATE="2024-09-10" STARTDATE="2024-09-10" ENDDATE="2079-06-06" ISACTIVE="1" PATH="103401.95232505.103550.103265.165173426" /><ITEM ID="235605513" OBJECTID="165173446" PARENTOBJID="105679" CHANGEID="600832267" OKTMO="26720000001" PREVID="0" NEXTID="0" UPDATEDATE="2024-09-10" STARTDATE="2024-09-10" ENDDATE="2079-06-06" ISACTIVE="1" PATH="103401.95232505.103550.105679.165173446" /><ITEM ID="235629988" OBJECTID="165197800" PARENTOBJID="161292806" CHANGEID="600893394" OKTMO="26715000001" PREVID="0" NEXTID="0" UPDATEDATE="2024-09-11" STARTDATE="2024-09-11" ENDDATE="2079-06-06" ISACTIVE="1" PATH="103401.95232504.103493.161292806.165197800" /><ITEM ID="235630004" OBJECTID="165197816" PARENTOBJID="105006" CHANGEID="600893410" OKTMO="26715000001" PREVID="0" NEXTID="0" UPDATEDATE="2024-09-11" STARTDATE="2024-09-11" ENDDATE="2079-06-06" ISACTIVE="1" PATH="103401.95232504.103493.105006.165197816" /><ITEM ID="235629995" OBJECTID="165197807" PARENTOBJID="12652761" CHANGEID="600893401" OKTMO="26715000001" PREVID="0" NEXTID="0" UPDATEDATE="2024-09-11" STARTDATE="2024-09-11" ENDDATE="2079-06-06" ISACTIVE="1" PATH="103401.95232504.103493.103794.12652761.165197807" /></ITEMS>